README.md
setup.cfg
setup.py
DIVESH/__init__.py
DIVESH/topsis.py
Topsis_Divesh_101903610.egg-info/PKG-INFO
Topsis_Divesh_101903610.egg-info/SOURCES.txt
Topsis_Divesh_101903610.egg-info/dependency_links.txt
Topsis_Divesh_101903610.egg-info/top_level.txt